jupyterlab_primehub/__init__.py
jupyterlab_primehub/_version.py
jupyterlab_primehub/api.py
jupyterlab_primehub/handlers.py
jupyterlab_primehub/utils.py
jupyterlab_primehub/labextension/infuseai-jupyterlab-primehub-0.1.3.tgz
jupyterlab_primehub/labextension/infuseai-jupyterlab-primehub-0.1.4.tgz
jupyterlab_primehub-0.1.4.data/data/etc/jupyter/jupyter_notebook_config.d/jupyterlab_primehub.json
jupyterlab_primehub-0.1.4.data/data/share/jupyter/lab/extensions/infuseai-jupyterlab-primehub-0.1.4.tgz
jupyterlab_primehub-0.1.4.dist-info/LICENSE
jupyterlab_primehub-0.1.4.dist-info/METADATA
jupyterlab_primehub-0.1.4.dist-info/WHEEL
jupyterlab_primehub-0.1.4.dist-info/top_level.txt
jupyterlab_primehub-0.1.4.dist-info/RECORD
