Metadata-Version: 2.1
Name: jupyterlab-primehub
Version: 0.1.4
Summary: A JupyterLab server extension
Home-page: https://github.com/InfuseAI/primehub-job
Author: InfuseAI
License: BSD-3-Clause
Keywords: Jupyter,JupyterLab
Platform: Linux
Platform: Mac OS X
Platform: Windows
Classifier: License :: OSI Approved :: BSD License
Classifier: Programming Language :: Python
Classifier: Programming Language :: Python :: 3
Classifier: Programming Language :: Python :: 3.5
Classifier: Programming Language :: Python :: 3.6
Classifier: Programming Language :: Python :: 3.7
Classifier: Programming Language :: Python :: 3.8
Classifier: Framework :: Jupyter
Requires-Dist: jupyterlab (~=2.0)
Requires-Dist: primehub-job
Requires-Dist: papermill (~=2.3.0)
